strongly/__init__.py
strongly/api_client.py
strongly/exceptions.py
tests/__init__.py
tests/conftest.py
tests/test_exceptions.py
tests/test_strongly.py
strongly-0.4.dist-info/METADATA
strongly-0.4.dist-info/WHEEL
strongly-0.4.dist-info/top_level.txt
strongly-0.4.dist-info/RECORD
