Metadata-Version: 2.1
Name: strongly
Version: 0.4
Summary: A Python client for the Strongly.AI API
Home-page: https://github.com/strongly-ai/strongly
Author: StronglyAI, Inc.
Author-email: info@strongly.ai
Requires-Dist: requests
Requires-Dist: python-dotenv
